syft_widget/__init__.py
syft_widget/cli.py
syft_widget/display_objects.py
syft_widget/endpoints.py
syft_widget/managed_widget.py
syft_widget/process_tracker.py
syft_widget/production.py
syft_widget/server.py
syft_widget/syftbox_manager.py
syft_widget/widget.py
syft_widget/widget_registry.py
syft_widget-0.2.0.dist-info/licenses/LICENSE
syft_widget-0.2.0.dist-info/METADATA
syft_widget-0.2.0.dist-info/WHEEL
syft_widget-0.2.0.dist-info/top_level.txt
syft_widget-0.2.0.dist-info/RECORD
