Metadata-Version: 2.4
Name: syft-widget
Version: 0.2.0
Summary: A toolkit for interactive Jupyter widgets with server/snapshot switching
Author-email: Your Name <your.email@example.com>
Requires-Python: >=3.9
License-File: LICENSE
Requires-Dist: ipywidgets>=8.0.0
Requires-Dist: requests>=2.28.0
Requires-Dist: fastapi>=0.100.0
Requires-Dist: uvicorn>=0.23.0
Requires-Dist: syft_core>=0.1.0
Dynamic: license-file
